{"indice": 617, "titulo": "Harvard edX - Pesquisa Google", "url": "https://google.com/search?ie=UTF-8&q=Harvard+edX&sa=X&ved=2ahUKEwietIGNw-HzAhUCrpUCHVMADnYQ1QJ6BAgEEAY", "texto": "Harvard edX - Pesquisa Google G o o g l e G o o g l e \u00d7 Clique  aqui  se voc\u00ea n\u00e3o for redirecionado em alguns segundos.         Todas Not\u00edcias Imagens Shopping   Maps   V\u00eddeos   Livros   Ferramentas de pesquisa         Em qualquer idioma Em qualquer idioma Pesquisar p\u00e1ginas em Portugu\u00eas Em qualquer data Em qualquer data  Na \u00faltima hora  Nas \u00faltimas 24 horas  Na \u00faltima semana  No \u00faltimo m\u00eas  No \u00faltimo ano Todos os resultados Todos os resultados Ao p\u00e9 da letra Harvard University | edX www.edx.org \u203a school \u203a harvardx Harvard University is devoted to excellence in teaching, learning, and research, and to developing leaders in many disciplines who make a difference\u00a0... HarvardX  \u00b7  CS50's Web Programming  \u00b7  US Government XSeries ...  \u00b7  Justice edX | Free Online Courses by Harvard, MIT, & more | edX www.edx.org Explore top courses \u00b7 Computer Science \u00b7 Programming for. Everybody (Getting Started with Python)\u2026 \u00b7 Computer Science 101\u2026 \u00b7 Introduction to Cloud Development with\u00a0... Harvard University  \u00b7  Login  \u00b7  edX For Business  \u00b7  Open edX As pessoas tamb\u00e9m perguntam Are Harvard edX certificates worth it? Is edX really Harvard? Is edX Harvard FREE? Is HarvardX the same as Harvard? Login - Register | edX authn.edx.org \u203a login edX and its Members use cookies and other tracking technologies for performance, analytics, and marketing purposes. By using this website, you accept this\u00a0... CS50: Computer Science Courses and Programs from Harvard | edX www.edx.org \u203a ... Introduction to Computer Science from Harvard, better known as CS50, is the largest course on the Harvard campus and more than 2,000,000 learners worldwide\u00a0... HarvardX - Harvard University harvardx.harvard.edu N\u00e3o h\u00e1 nenhuma informa\u00e7\u00e3o dispon\u00edvel para esta p\u00e1gina. \u00b7  Saiba o motivo Imagens Ver tudo Ver tudo HarvardX - Office of the Vice Provost for Advances in Learning vpal.harvard.edu \u203a harvard-online-harvardx Launched in parallel with edX (a non-profit learning platform founded by Harvard and MIT), HarvardX independently represents Harvard's academic diversity,\u00a0... Justice Today: Money, Markets, and Morals (edX) | Harvard University online-learning.harvard.edu \u203a course \u203a justice-today-... Justice Today: Money, Markets, and Morals (edX) ... Led by award-winning Harvard Professor Michael J. Sandel, professor of the popular HarvardX course\u00a0... EdX: Site tem cursos gratuitos com professores de Harvard e MIT economia.uol.com.br \u203a noticias \u203a redacao \u203a 2021/06/27 \u203a cursos-online-ha... A plataforma de educa\u00e7\u00e3o online Edx, da Universidade Harvard e pelo MIT (Instituto de Tecnologia de Massachusetts), ambos dos Estados Unidos\u00a0... Dura\u00e7\u00e3o:  0:45 Data da postagem:  27 de jun. de 2021 edX: a plataforma de cursos online e gratuitos de Harvard www.estudarfora.org.br \u203a tag \u203a edx Plataforma edX, mantida pelas universidades de Harvard e MIT, oferece mais de 60 op\u00e7\u00f5es de cursos totalmente gratuitos e online. Aproveite o recurso e tenha\u00a0... Pesquisas relacionadas edX Harvard cursos gratuitos edX cursos Harvard edX login Justice Harvard edX Harvard online courses free edX Harvard CS50 edX Brasil Data Science Harvard edX     Mais >     73805, Formosa - GO \u00a0-\u00a0 Do seu endere\u00e7o IP \u00a0-\u00a0 Saiba mais Fazer login Configura\u00e7\u00f5es Privacidade Termos  ", "encoding": "utf-8"}