{"indice": 68, "titulo": "O que \u00e9 um amigo para voc\u00ea - Pesquisa Google", "url": "https://google.com/search?ie=UTF-8&q=O+que+%C3%A9+um+amigo+para+voc%C3%AA&sa=X&ved=2ahUKEwiUhPz_wOHzAhVNqJUCHTPjC90Q1QJ6BAgFEBA", "texto": "O que \u00e9 um amigo para voc\u00ea - Pesquisa Google G o o g l e G o o g l e \u00d7 Clique  aqui  se voc\u00ea n\u00e3o for redirecionado em alguns segundos.         Todas V\u00eddeos Imagens Not\u00edcias   Maps   Shopping   Livros   Ferramentas de pesquisa         Em qualquer idioma Em qualquer idioma Pesquisar p\u00e1ginas em Portugu\u00eas Em qualquer data Em qualquer data  Na \u00faltima hora  Nas \u00faltimas 24 horas  Na \u00faltima semana  No \u00faltimo m\u00eas  No \u00faltimo ano Todos os resultados Todos os resultados Ao p\u00e9 da letra Amizade Ver tudo Amizade \u00e9 uma rela\u00e7\u00e3o afetiva, a princ\u00edpio sem caracter\u00edsticas rom\u00e2ntico-sexuais, entre duas pessoas. Em sentido amplo, \u00e9 um relacionamento humano que envolve o conhecimento m\u00fatuo e a afei\u00e7\u00e3o, al\u00e9m de lealdade ao ponto do altru\u00edsmo.  Wikip\u00e9dia As pessoas tamb\u00e9m perguntam O que \u00e9 ser amigo para voc\u00ea? O que \u00e9 um amigo de verdade? Qual o significado de amigo e colega? O que \u00e9 um amigo texto? O que \u00e9 um amigo para voc\u00ea? - Artigos - Campo Grande News www.campograndenews.com.br \u203a artigos \u203a o-que-e-um-amigo-para-voce 19 de jul. de 2017  \u00b7  Para Epicuro, \u201ca amizade \u00e9 o m\u00e1ximo que a sabedoria da felicidade pode proporcionar na vida\u201d. Segundo Arist\u00f3teles, \u201camigo \u00e9 uma \u00fanica alma\u00a0... Para voc\u00ea, oque \u00e9 amigo? Em prosa ou em verso, escreva - Brainly brainly.com.br \u203a Portugu\u00eas \u203a Ensino fundamental (b\u00e1sico) Amigo \u00e9 uma pessoa que em todo momento est\u00e1 contigo.\u00c9 aquele que em todas as situa\u00e7\u00f5es voc\u00ea pode contar com ele, como se fosse um irm\u00e3o! Significado de Amigo (O que \u00e9, Conceito e Defini\u00e7\u00e3o) www.significados.com.br \u203a amigo 31 de out. de 2013  \u00b7  O que \u00e9 Amigo: Conceito e Significado de Amigo: Amigo \u00e9 o nome que se d\u00e1 a um indiv\u00edduo que mant\u00e9m um relacionamento de afeto,\u00a0... O que um Amigo Significa - Pensador www.pensador.com \u203a o_que_um_amigo_significa Se voc\u00ea convive com imprevistos, \u00e9 porque ainda n\u00e3o se abriu para outras percep\u00e7\u00f5es, continua olhando com a mente, n\u00e3o ampliou para seu melhor \u00e2ngulo, a vis\u00e3o\u00a0... O que \u00e9 ser amigo? - YouTube www.youtube.com \u203a watch 11 de out. de 2016  \u00b7  Voc\u00ea da mais import\u00e2ncia aos amigos ou as redes sociais? Amigo \u00e9 o nome que se d\u00e1 a ... Dura\u00e7\u00e3o:  6:51 Data da postagem:  11 de out. de 2016 Que tipo de amigo voc\u00ea \u00e9? - YouTube www.youtube.com \u203a watch 13 de nov. de 2020  \u00b7  Hoje compartilho com voc\u00eas a felicidade que senti por realiza\u00e7\u00f5es que meus amigos tiveram ... Dura\u00e7\u00e3o:  2:23 Data da postagem:  13 de nov. de 2020 A import\u00e2ncia da amizade na vida de uma pessoa - Cl\u00ednica Pr\u00f3-Sa\u00fade clinprosaude.com.br \u203a a-importancia-da-amizade-na-vida-de-uma-pessoa Um amigo te mostra onde voc\u00ea est\u00e1 errando, n\u00e3o para apontar o dedo, mas sim para ver o seu crescimento e evolu\u00e7\u00e3o. Uma amizade se trata de reciprocidade, se\u00a0... Um amigo como voc\u00ea - Mundo das Mensagens www.mundodasmensagens.com \u203a mensagem \u203a um-amigo-como-voce Mensagem: Um amigo como voc\u00ea Meu cora\u00e7\u00e3o bate de gratid\u00e3o por Deus ter colocado um amigo como voc\u00ea no meu caminho! Que tipo de amigo voc\u00ea \u00e9? Fa\u00e7a o teste e descubra | Como Ser\u00e1 | G1 g1.globo.com \u203a como-sera \u203a quiz \u203a que-tipo-de-amigo-voce-e-faca-o-teste... 20 de jul. de 2019  \u00b7  O quadro 'Hoje \u00e9 dia de...', do 'Como Ser\u00e1?', vai celebrar o Dia do Amigo neste s\u00e1bado (20). E a gente quer saber: que tipo de amigo voc\u00ea \u00e9? O que significa ser amigo para voc\u00ea? Para... - Facebook sw-ke.facebook.com \u203a amigosdohc \u203a videos \u203a o-que-significa-ser-amigo-p... 18 de abr. de 2021  \u00b7  O que significa ser amigo para voc\u00ea? Para n\u00f3s, amigo significa muitas coisas, mas ... Dura\u00e7\u00e3o:  1:35 Data da postagem:  18 de abr. de 2021 Pesquisas relacionadas O que \u00e9 ser amigo brainly O que \u00e9 um amigo de verdade Reflex\u00e3o sobre o que \u00e9 ser amigo O que \u00e9 um melhor amigo O que \u00e9 ser amigo de verdade texto Amigo significado aur\u00e9lio Significado de amigo na B\u00edblia Amigo em ingl\u00eas     Mais >     73805, Formosa - GO \u00a0-\u00a0 Do seu endere\u00e7o IP \u00a0-\u00a0 Saiba mais Fazer login Configura\u00e7\u00f5es Privacidade Termos  ", "encoding": "utf-8"}