{"indice": 797, "titulo": "Hor\u00e1rio de Bras\u00edlia - Pesquisa Google", "url": "https://google.com/search?ie=UTF-8&q=Hor%C3%A1rio+de+Bras%C3%ADlia&sa=X&ved=2ahUKEwjvyKnpw-HzAhUfqZUCHem9DV8Q1QJ6BAgEEAY", "texto": "Hor\u00e1rio de Bras\u00edlia - Pesquisa Google G o o g l e G o o g l e \u00d7 Clique  aqui  se voc\u00ea n\u00e3o for redirecionado em alguns segundos.         Todas Not\u00edcias Imagens Shopping   Maps   V\u00eddeos   Livros   Ferramentas de pesquisa         Em qualquer idioma Em qualquer idioma Pesquisar p\u00e1ginas em Portugu\u00eas Em qualquer data Em qualquer data  Na \u00faltima hora  Nas \u00faltimas 24 horas  Na \u00faltima semana  No \u00faltimo m\u00eas  No \u00faltimo ano Todos os resultados Todos os resultados Ao p\u00e9 da letra Bras\u00edlia - DF  /  Hora local 18:59 s\u00e1bado, 23 de outubro de 2021\nHor\u00e1rio em Bras\u00edlia - DF Hor\u00e1rio de Bras\u00edlia - Hora Certa Oficial do Brasil www.horariodebrasilia.org Acerte seu rel\u00f3gio com o hor\u00e1rio de Bras\u00edlia, a hora certa oficial do Brasil. As pessoas tamb\u00e9m perguntam Onde ver a hora certa? Qual o hor\u00e1rio nacional de Bras\u00edlia? Qual \u00e9 a UTC do Brasil? Qual o fuso hor\u00e1rio do Canad\u00e1? Hora em Bras\u00edlia, Brasil agora - Time.is time.is \u203a pt_br \u203a Bras\u00edlia Hora exata agora, fuso hor\u00e1rio, diferen\u00e7a entre hor\u00e1rios, hor\u00e1rios do nascer/p\u00f4r do sol e informa\u00e7\u00f5es chave para Bras\u00edlia, Brasil. Hor\u00e1rio de Bras\u00edlia - RelogioOnline.com.br relogioonline.com.br \u203a horario \u203a bras\u00edlia Hora certa Bras\u00edlia. Diferen\u00e7a de Hor\u00e1rio Local: Amanh\u00e3, +4 H. Fuso hor\u00e1rio: (UTC/GMT -\u00a0... Hora atual, fuso horario, e hor\u00e1rio de ver\u00e3o em Bras\u00edlia, Brasil 24timezones.com \u203a Hora mundial \u203a Brasil Que horas s\u00e3o em Bras\u00edlia agora? Verifique o fuso hor\u00e1rio, quando come\u00e7a e quando termina o horario de ver\u00e3o de 2021, e outras informa\u00e7\u00f5es. Hor\u00e1rio de Bras\u00edlia - Hora Certa - Horario oficial de Brasilia www.horario-brasilia.com O hor\u00e1rio de Bras\u00edlia \u00e9 UTC -3, ou seja, tr\u00eas horas a menos que Tempo Universal Coordenado. Tamb\u00e9m h\u00e1 o fato de ser adotado o hor\u00e1rio de ver\u00e3o, ou seja, na\u00a0... Hor\u00e1rio de Bras\u00edlia - Hora certa e oficial do Brasil - Calendarr www.calendarr.com \u203a brasil \u203a horario-de-brasilia A hora oficial do Brasil (UTC-3) \u00e9 o hor\u00e1rio de Bras\u00edlia, capital do Pa\u00eds. O Brasil possui 4 fusos hor\u00e1rios: UTC-2: Fuso hor\u00e1rio do arquip\u00e9lago de S\u00e3o Pedro\u00a0... Hora Legal Brasileira - DSHO www.horalegalbrasil.mct.on.br \u203a HoraLegalBrasileira Divis\u00e3o Servi\u00e7o da Hora - DSHO Hora Legal Brasileira. Hora Oficial de Bras\u00edlia ... Fusos hor\u00e1rios adotados na Hora Legal Brasileira em refer\u00eancia ao Tempo\u00a0... Hor\u00e1rio de Bras\u00edlia - Hora certa - hor\u00e1rio oficial do Brasil www.horariodebrasilia.info Hor\u00e1rio de Bras\u00edlia - Acerte seu rel\u00f3gio com a hora certa oficial do Brasil. HORA DE BRAS\u00cdLIA - O hor\u00e1rio oficial do Brasil www.horadebrasilia.com O site Hora de Bras\u00edlia traz a informa\u00e7\u00e3o do hor\u00e1rio oficial do Brasil. Acesse o site e confira a hora certa. Como calcular o hor\u00e1rio GMT para o hor\u00e1rio de Brasilia? 150.163.141.175 \u203a faq \u203a como-calcular-o-horario-gmt-para-o-horario-de-... Para transformar o hor\u00e1rio GMT no hor\u00e1rio de Bras\u00edlia (hor\u00e1rio oficial brasileiro) \u00e9 necess\u00e1rio subtrair 3 horas (-3 horas) do. Pesquisas relacionadas Hor\u00e1rio de Bras\u00edlia segundos Hor\u00e1rio de Brasil Hor\u00e1rio de Bras\u00edlia GMT Hora certa Hor\u00e1rio de S\u00e3o Paulo Hora certa segundos Hora certa tela cheia Fuso hor\u00e1rio par\u00e1     Mais >     73805, Formosa - GO \u00a0-\u00a0 Do seu endere\u00e7o IP \u00a0-\u00a0 Saiba mais Fazer login Configura\u00e7\u00f5es Privacidade Termos  ", "encoding": "utf-8"}