{"indice": 52, "title": "test - Pesquisa Google", "url": "https://www.google.com.br/search?q=test&gbv=1&ie=UTF-8&ei=9fpzYZ3sAb3K1sQPksah8AU&start=10&sa=N", "text": "test - Pesquisa GoogleGoogleGoogle    TodasNot\u00ef\u00bf\u00bdciasMapsImagens V\u00ef\u00bf\u00bddeos Shopping Livros Ferramentas de pesquisa    Qualquer pa\u00ef\u00bf\u00bdsQualquer pa\u00ef\u00bf\u00bdsPa\u00ef\u00bf\u00bds: BrasilEm qualquer idiomaEm qualquer idiomaP\u00ef\u00bf\u00bdginas em portugu\u00ef\u00bf\u00bdsEm qualquer dataEm qualquer data Na \u00ef\u00bf\u00bdltima hora Nas \u00ef\u00bf\u00bdltimas 24 horas Na \u00ef\u00bf\u00bdltima semana No \u00ef\u00bf\u00bdltimo m\u00ef\u00bf\u00bds No \u00ef\u00bf\u00bdltimo anoTodos os resultadosTodos os resultadosAo p\u00ef\u00bf\u00bd da letraFestival em novembro ter\u00ef\u00bf\u00bd lan\u00ef\u00bf\u00bdamentos de motos e test-ride ... - UOLwww.uol.com.br \u203a carros \u203a colunas \u203a infomoto \u203a 2021/10/21 \u203a festival-em...h\u00ef\u00bf\u00bd 2 dias \u00ef\u00bf\u00bd Durante o festival, os visitantes tamb\u00ef\u00bf\u00bdm ter\u00ef\u00bf\u00bdo a oportunidade de fazer test-ride com diversos modelos na lend\u00ef\u00bf\u00bdria pista de 4.309 metros de\u00ef\u00bf\u00bd...TEST \u2013 GRINDCOREwww.testdeath.com.brO Jogo Humano. 2019. O Jogo Humano. Esp\u00ef\u00bf\u00bdcies. 2015. Esp\u00ef\u00bf\u00bdcies. Arabe Macabre. 2012. Arabe Macabre. EP'S. Bal\u00ef\u00bf\u00bdo de Azar. 2013. Bal\u00ef\u00bf\u00bdo de Azar. M' Boi Mirim.Regular rapid lateral flow coronavirus (COVID-19) tests - NHSwww.nhs.uk \u203a coronavirus-covid-19 \u203a testing \u203a regu...Find out how to get regular rapid lateral flow tests for coronavirus (COVID-19) if you do not have symptoms and why regular testing is important.Rich Results Test - Google Search Consolesearch.google.com \u203a test \u203a rich-resultsWhat is this test? Test your publicly accessible page to see which rich results can be generated by the structured data it contains.ICC Test Match Player Rankings International Cricket Councilwww.icc-cricket.com \u203a rankings \u203a mens \u203a testOfficial International Cricket Council rankings for test match cricket players. Discover latest ICC rankings table, predict upcoming matches, see points and\u00ef\u00bf\u00bd...Covid: PCR test not needed for fully vaccinated travellers - BBC Newswww.bbc.com \u203a news \u203a uk-wales-59008770h\u00ef\u00bf\u00bd 21 horas \u00ef\u00bf\u00bd From the end of the month vaccinated people returning to Wales can take a lateral flow test instead.Internet Speed Test - Check Your Internet Speed | Coxwww.cox.com \u203a residential \u203a support \u203a speedtestHow fast is your internet right now? Use the Cox Speed Test to check upload and download speeds. Also discover ways to improve both internet and wifi\u00ef\u00bf\u00bd...Duolingo English Test Readinessenglishtest.duolingo.com \u203a readinessAdaptive testing \u00ef\u00bf\u00bd All question types are integrated in a single section \u00ef\u00bf\u00bd The question types appear randomly \u00ef\u00bf\u00bd The difficulty of the questions changes for each\u00ef\u00bf\u00bd...Test your English - Young Learnerswww.cambridgeenglish.org \u203a test-your-english \u203a yo...This is a quick, free online English test for children and young learners. It will tell you which Cambridge English exam may be best for you.Writing tests | Postman Learning Centerlearning.postman.com \u203a writing-scripts \u203a test-scriptsWriting tests. You can write test scripts for your Postman API requests in JavaScript. Tests allow you to ensure that your API is working as expected,\u00ef\u00bf\u00bd...Medidor de velocidade - Medir download, upload e pingAn\u00ef\u00bf\u00bdnciowww.busqnet.com/Internet lenta? Veja se sua operadora est\u00ef\u00bf\u00bd entregando a velocidade contratada. Teste agora. Descubra em segundos se sua internet est\u00ef\u00bf\u00bd r\u00ef\u00bf\u00bdpida como deveria, fa\u00ef\u00bf\u00bda o teste! Ping lento. Medir upload. Medir download. Medir Ping.Speedtest - Velocimetro - Veloc\u00ef\u00bf\u00bdmetro de internetAn\u00ef\u00bf\u00bdnciowww.melhorescolha.com/speedtestAproveite e verifique tamb\u00ef\u00bf\u00bdm planos de internet mais r\u00ef\u00bf\u00bdpidos dispon\u00ef\u00bf\u00bdveis na sua regi\u00ef\u00bf\u00bdo. Confira se a velocidade da sua internet \u00ef\u00bf\u00bd a que voc\u00ef\u00bf\u00bd realmente espera. Descubra j\u00ef\u00bf\u00bd! Internet residencial. Teste de download. Teste de lat\u00ef\u00bf\u00bdncia. Teste de ping. Teste de wifi. Teste de upload. Teste residencial. Teste de 4G.Combos para economizar. \u00ef\u00bf\u00bd TV por assinatura \u00ef\u00bf\u00bd Telefone fixo.  <P\u00ef\u00bf\u00bdgina 2>  St. de Grandes \u00ef\u00bf\u00bdreas Norte - Asa Norte, Bras\u00ef\u00bf\u00bdlia - DF\u00a0-\u00a0Do seu endere\u00ef\u00bf\u00bdo IP\u00a0-\u00a0Saiba maisFazer loginConfigura\u00ef\u00bf\u00bd\u00ef\u00bf\u00bdesPrivacidadeTermos ", "encoding": "iso-8859-1"}