{"indice": 172, "title": "test - Google Shopping", "url": "https://www.google.com.br/search?q=test&ie=UTF-8&tbm=shop&source=lnms&sa=X&ved=0ahUKEwjQu7XAv-DzAhURpZUCHRdADjwQ_AUIDCgF", "text": "test - Google ShoppingGoogle\u00ef\u00bf\u00bdTodasShoppingImagensMapsV\u00ef\u00bf\u00bddeosNot\u00ef\u00bf\u00bdciasLivrosPre\u00ef\u00bf\u00bdoAt\u00ef\u00bf\u00bd R$\u00ef\u00bf\u00bd500R$\u00ef\u00bf\u00bd500 \u2013 R$\u00ef\u00bf\u00bd3.000Acima de R$\u00ef\u00bf\u00bd3.000Condi\u00ef\u00bf\u00bd\u00ef\u00bf\u00bdoItens novosItens usadosVendedorMago PsicologiaTalch\u00ef\u00bf\u00bdEstante VirtualMercado LivreSobre \u24d8Kit Genera DNA Teste de Ancestralidade B\u00ef\u00bf\u00bdsicoR$\u00ef\u00bf\u00bd199,00 de GeneratestR$\u00ef\u00bf\u00bd1,00 de BrasilazyProduto De TesteR$\u00ef\u00bf\u00bd0,01 de Espa\u00ef\u00bf\u00bdo Pel\u00ef\u00bf\u00bdciatesteR$\u00ef\u00bf\u00bd2,00 de Espa\u00ef\u00bf\u00bdo Fashion kidsProduto de testeR$\u00ef\u00bf\u00bd1,00 de Livre e LeveTesteR$\u00ef\u00bf\u00bd1,50 de Tokari Materiais de Constru\u00ef\u00bf\u00bd\u00ef\u00bf\u00bdoteste-NOVOR$\u00ef\u00bf\u00bd1,00 de BodebrowntestR$\u00ef\u00bf\u00bd1,00 de SubmarinotestR$\u00ef\u00bf\u00bd1,00 de Americanas.comTeste O Que Voc\u00ef\u00bf\u00bd SenteR$\u00ef\u00bf\u00bd80,00 de Mago PsicologiatesteR$\u00ef\u00bf\u00bd1,00 de Back WashtesteR$\u00ef\u00bf\u00bd9,00 de ShoptimeTESTE AUAHA N/COMPRAR BrancaR$\u00ef\u00bf\u00bd10.545,00 de EmbralumiProduto TesteR$\u00ef\u00bf\u00bd5,90 de eCordetesteR$\u00ef\u00bf\u00bd9,00 de SubmarinoProduto TesteR$\u00ef\u00bf\u00bd1,00 de MotobikersProduto de TestesR$\u00ef\u00bf\u00bd1,00 de P\u00ef\u00bf\u00bd Grande Cal\u00ef\u00bf\u00bdadosTeste De Qualidade Da \u00ef\u00bf\u00bdgua Medidor De Teste Digital De \u00ef\u00bf\u00bdguaR$\u00ef\u00bf\u00bd84,87 de Mercado LivreTestR$\u00ef\u00bf\u00bd0,06 de AliExpress.comProduto testeR$\u00ef\u00bf\u00bd1,00 de PAC Cosm\u00ef\u00bf\u00bdticosMais >Fazer loginConfigura\u00ef\u00bf\u00bd\u00ef\u00bf\u00bdes de Pesquisa -\u00a0Privacidade -\u00a0TermosSetor de Grandes \u00ef\u00bf\u00bdreas Norte - Asa Norte, Bras\u00ef\u00bf\u00bdlia - DF\u00a0\u00b7\u00a0Learn more", "encoding": "iso-8859-1"}